Eve/__init__.py
Eve/algo/__init__.py
Eve/algo/default_eval_method.py
Eve/algo/default_search_space.py
Eve/algo/random_search.py
Eve/algo/utils.py
Eve/split/__init__.py
Eve/split/_split.py
Eve/split/split.py
eve_viz-0.0b18.dist-info/LICENSE
eve_viz-0.0b18.dist-info/METADATA
eve_viz-0.0b18.dist-info/WHEEL
eve_viz-0.0b18.dist-info/top_level.txt
eve_viz-0.0b18.dist-info/RECORD
