Metadata-Version: 2.1
Name: eve-viz
Version: 0.0b18
Summary: An easy to use tool for parallel model evaluation tasks, with native support for the random search algorithm.
Home-page: https://github.com/mozjay0619/eve-viz
Author: Jay Kim
License: DSB 3-clause
Platform: UNKNOWN
